{
    "resultCode": "00",
    "resultMsg": "SUCCESS",
    "items": [
        {
            "gpId": "_KNCC_CKUP",
            "colDesc": "환자대체번호",
            "num": 1,
            "dataType": "STRING",
            "colCnt": 45003,
            "gpNm": "검사",
            "colNm": "환자대체번호",
            "tblId": "_KNCC_QS_CKUP",
            "colId": "PT_SBST_NO",
            "tblNm": "검사",
            "dispFormat": "RN00000000"
        },
        {
            "gpId": "_KNCC_CKUP",
            "colDesc": "방문일자",
            "num": 2,
            "dataType": "DATE",
            "colCnt": 0,
            "gpNm": "검사",
            "colNm": "방문일자",
            "tblId": "_KNCC_QS_CKUP",
            "colId": "VYEAR",
            "tblNm": "검사",
            "dispFormat": "YYYY-MM-DD"
        },
        {
            "gpId": "_KNCC_CKUP",
            "colDesc": "위내시경검사",
            "num": 3,
            "dataType": "STRING",
            "colCnt": 45003,
            "gpNm": "검사",
            "colNm": "위내시경검사",
            "tblId": "_KNCC_QS_CKUP",
            "colId": "ENDOSCOP",
            "tblNm": "검사",
            "dispFormat": "1=있다"
        },
        {
            "gpId": "_KNCC_CKUP",
            "colDesc": "위내시경검진이유_이상증상",
            "num": 4,
            "dataType": "STRING",
            "colCnt": 45003,
            "gpNm": "검사",
            "colNm": "위내시경검진이유_이상증상",
            "tblId": "_KNCC_QS_CKUP",
            "colId": "ENDORE_1",
            "tblNm": "검사",
            "dispFormat": "값이 존재할 경우 이상증상"
        },
        {
            "gpId": "_KNCC_CKUP",
            "colDesc": "위내시경검진이유_정기검진",
            "num": 5,
            "dataType": "STRING",
            "colCnt": 45003,
            "gpNm": "검사",
            "colNm": "위내시경검진이유_정기검진",
            "tblId": "_KNCC_QS_CKUP",
            "colId": "ENDORE_2",
            "tblNm": "검사",
            "dispFormat": "값이 존재할 경우 정기검진"
        },
        {
            "gpId": "_KNCC_CKUP",
            "colDesc": "위내시경받은횟수",
            "num": 6,
            "dataType": "INTEGER",
            "colCnt": 29796,
            "gpNm": "검사",
            "colNm": "위내시경받은횟수",
            "tblId": "_KNCC_QS_CKUP",
            "colId": "ENDONUM",
            "tblNm": "검사",
            "dispFormat": "1-9, 모름=9999"
        },
        {
            "gpId": "_KNCC_CKUP",
            "colDesc": "위내시경검사결과기타",
            "num": 7,
            "dataType": "STRING",
            "colCnt": 45003,
            "gpNm": "검사",
            "colNm": "위내시경검사결과기타",
            "tblId": "_KNCC_QS_CKUP",
            "colId": "ENDOSANR",
            "tblNm": "검사",
            "dispFormat": "기타 검사결과 텍스트값"
        },
        {
            "gpId": "_KNCC_CKUP",
            "colDesc": "위내시경처음검사",
            "num": 8,
            "dataType": "STRING",
            "colCnt": 45003,
            "gpNm": "검사",
            "colNm": "위내시경처음검사",
            "tblId": "_KNCC_QS_CKUP",
            "colId": "ENDOFYR",
            "tblNm": "검사",
            "dispFormat": "YYYY, 모름=9999"
        },
        {
            "gpId": "_KNCC_CKUP",
            "colDesc": "위내시경마지막검사",
            "num": 9,
            "dataType": "STRING",
            "colCnt": 45003,
            "gpNm": "검사",
            "colNm": "위내시경마지막검사",
            "tblId": "_KNCC_QS_CKUP",
            "colId": "ENDOLYR",
            "tblNm": "검사",
            "dispFormat": "YYYY, 모름=9999"
        },
        {
            "gpId": "_KNCC_CKUP",
            "colDesc": "위내시경검사결과_정상",
            "num": 10,
            "dataType": "STRING",
            "colCnt": 45003,
            "gpNm": "검사",
            "colNm": "위내시경검사결과_정상",
            "tblId": "_KNCC_QS_CKUP",
            "colId": "ENDOSNR_1",
            "tblNm": "검사",
            "dispFormat": "값이 존재할 경우 정상"
        },
        {
            "gpId": "_KNCC_CKUP",
            "colDesc": "위내시경검사결과_위염",
            "num": 11,
            "dataType": "STRING",
            "colCnt": 45003,
            "gpNm": "검사",
            "colNm": "위내시경검사결과_위염",
            "tblId": "_KNCC_QS_CKUP",
            "colId": "ENDOSNR_2",
            "tblNm": "검사",
            "dispFormat": "값이 존재할 경우 위염"
        },
        {
            "gpId": "_KNCC_CKUP",
            "colDesc": "위내시경검사결과_궤양",
            "num": 12,
            "dataType": "STRING",
            "colCnt": 45003,
            "gpNm": "검사",
            "colNm": "위내시경검사결과_궤양",
            "tblId": "_KNCC_QS_CKUP",
            "colId": "ENDOSNR_3",
            "tblNm": "검사",
            "dispFormat": "값이 존재할 경우 궤양"
        },
        {
            "gpId": "_KNCC_CKUP",
            "colDesc": "위내시경검사결과_식도염",
            "num": 13,
            "dataType": "STRING",
            "colCnt": 45003,
            "gpNm": "검사",
            "colNm": "위내시경검사결과_식도염",
            "tblId": "_KNCC_QS_CKUP",
            "colId": "ENDOSNR_4",
            "tblNm": "검사",
            "dispFormat": "값이 존재할 경우 식도염"
        },
        {
            "gpId": "_KNCC_CKUP",
            "colDesc": "위내시경검사결과_암",
            "num": 14,
            "dataType": "STRING",
            "colCnt": 45003,
            "gpNm": "검사",
            "colNm": "위내시경검사결과_암",
            "tblId": "_KNCC_QS_CKUP",
            "colId": "ENDOSNR_5",
            "tblNm": "검사",
            "dispFormat": "값이 존재할 경우 암"
        },
        {
            "gpId": "_KNCC_CKUP",
            "colDesc": "위내시경검사결과_용종",
            "num": 15,
            "dataType": "STRING",
            "colCnt": 45003,
            "gpNm": "검사",
            "colNm": "위내시경검사결과_용종",
            "tblId": "_KNCC_QS_CKUP",
            "colId": "ENDOSNR_6",
            "tblNm": "검사",
            "dispFormat": "값이 존재할 경우 용종"
        },
        {
            "gpId": "_KNCC_CKUP",
            "colDesc": "위내시경검사결과_기타",
            "num": 16,
            "dataType": "STRING",
            "colCnt": 45003,
            "gpNm": "검사",
            "colNm": "위내시경검사결과_기타",
            "tblId": "_KNCC_QS_CKUP",
            "colId": "ENDOSNR_7",
            "tblNm": "검사",
            "dispFormat": "값이 존재할 경우 기타사항"
        },
        {
            "gpId": "_KNCC_CKUP",
            "colDesc": "위조영술(상부위장관조영)",
            "num": 17,
            "dataType": "STRING",
            "colCnt": 45003,
            "gpNm": "검사",
            "colNm": "위조영술(상부위장관조영)",
            "tblId": "_KNCC_QS_CKUP",
            "colId": "UGI",
            "tblNm": "검사",
            "dispFormat": "1=있다"
        },
        {
            "gpId": "_KNCC_CKUP",
            "colDesc": "위조영술(상부위장관조영)검진이유_이상증상",
            "num": 18,
            "dataType": "STRING",
            "colCnt": 45003,
            "gpNm": "검사",
            "colNm": "위조영술(상부위장관조영)검진이유_이상증상",
            "tblId": "_KNCC_QS_CKUP",
            "colId": "UGIRE_1",
            "tblNm": "검사",
            "dispFormat": "값이 존재할 경우 이상증상"
        },
        {
            "gpId": "_KNCC_CKUP",
            "colDesc": "위조영술(상부위장관조영)검진이유_정기검진",
            "num": 19,
            "dataType": "STRING",
            "colCnt": 45003,
            "gpNm": "검사",
            "colNm": "위조영술(상부위장관조영)검진이유_정기검진",
            "tblId": "_KNCC_QS_CKUP",
            "colId": "UGIRE_2",
            "tblNm": "검사",
            "dispFormat": "값이 존재할 경우 정기검진"
        },
        {
            "gpId": "_KNCC_CKUP",
            "colDesc": "위조영술(상부위장관조영)받은횟수",
            "num": 20,
            "dataType": "INTEGER",
            "colCnt": 18384,
            "gpNm": "검사",
            "colNm": "위조영술(상부위장관조영)받은횟수",
            "tblId": "_KNCC_QS_CKUP",
            "colId": "UGINUM",
            "tblNm": "검사",
            "dispFormat": "1-9, 모름=9999"
        },
        {
            "gpId": "_KNCC_CKUP",
            "colDesc": "위조영술(상부위장관조영)검사결과",
            "num": 21,
            "dataType": "STRING",
            "colCnt": 45003,
            "gpNm": "검사",
            "colNm": "위조영술(상부위장관조영)검사결과",
            "tblId": "_KNCC_QS_CKUP",
            "colId": "UGINR",
            "tblNm": "검사",
            "dispFormat": "1=정상"
        },
        {
            "gpId": "_KNCC_CKUP",
            "colDesc": "위조영술(상부위장관조영)정상이외",
            "num": 22,
            "dataType": "STRING",
            "colCnt": 45003,
            "gpNm": "검사",
            "colNm": "위조영술(상부위장관조영)정상이외",
            "tblId": "_KNCC_QS_CKUP",
            "colId": "UGIANR",
            "tblNm": "검사",
            "dispFormat": "텍스트"
        },
        {
            "gpId": "_KNCC_CKUP",
            "colDesc": "위조영술(상부위장관조영)처음검사",
            "num": 23,
            "dataType": "STRING",
            "colCnt": 45003,
            "gpNm": "검사",
            "colNm": "위조영술(상부위장관조영)처음검사",
            "tblId": "_KNCC_QS_CKUP",
            "colId": "UGIFYR",
            "tblNm": "검사",
            "dispFormat": "YYYY, 모름=9999"
        },
        {
            "gpId": "_KNCC_CKUP",
            "colDesc": "위조영술(상부위장관조영)마지막검사",
            "num": 24,
            "dataType": "STRING",
            "colCnt": 45003,
            "gpNm": "검사",
            "colNm": "위조영술(상부위장관조영)마지막검사",
            "tblId": "_KNCC_QS_CKUP",
            "colId": "UGILYR",
            "tblNm": "검사",
            "dispFormat": "YYYY, 모름=9999"
        },
        {
            "gpId": "_KNCC_CKUP",
            "colDesc": "대장내시경여부",
            "num": 25,
            "dataType": "STRING",
            "colCnt": 45003,
            "gpNm": "검사",
            "colNm": "대장내시경여부",
            "tblId": "_KNCC_QS_CKUP",
            "colId": "CSCOP",
            "tblNm": "검사",
            "dispFormat": "1=있다"
        },
        {
            "gpId": "_KNCC_CKUP",
            "colDesc": "대장내시경검진이유_이상증상",
            "num": 26,
            "dataType": "STRING",
            "colCnt": 45003,
            "gpNm": "검사",
            "colNm": "대장내시경검진이유_이상증상",
            "tblId": "_KNCC_QS_CKUP",
            "colId": "CSCOPRE_1",
            "tblNm": "검사",
            "dispFormat": "값이 존재할 경우 이상증상"
        },
        {
            "gpId": "_KNCC_CKUP",
            "colDesc": "대장내시경검진이유_정기검진",
            "num": 27,
            "dataType": "STRING",
            "colCnt": 45003,
            "gpNm": "검사",
            "colNm": "대장내시경검진이유_정기검진",
            "tblId": "_KNCC_QS_CKUP",
            "colId": "CSCOPRE_2",
            "tblNm": "검사",
            "dispFormat": "값이 존재할 경우 정기검진"
        },
        {
            "gpId": "_KNCC_CKUP",
            "colDesc": "대장내시경받은횟수",
            "num": 28,
            "dataType": "INTEGER",
            "colCnt": 22288,
            "gpNm": "검사",
            "colNm": "대장내시경받은횟수",
            "tblId": "_KNCC_QS_CKUP",
            "colId": "CSCOPNUM",
            "tblNm": "검사",
            "dispFormat": "1-9, 모름=9999"
        },
        {
            "gpId": "_KNCC_CKUP",
            "colDesc": "대장내시경검사결과",
            "num": 29,
            "dataType": "STRING",
            "colCnt": 45003,
            "gpNm": "검사",
            "colNm": "대장내시경검사결과",
            "tblId": "_KNCC_QS_CKUP",
            "colId": "CSCOPNR",
            "tblNm": "검사",
            "dispFormat": "1=정상"
        },
        {
            "gpId": "_KNCC_CKUP",
            "colDesc": "대장내시경정상이외",
            "num": 30,
            "dataType": "STRING",
            "colCnt": 45003,
            "gpNm": "검사",
            "colNm": "대장내시경정상이외",
            "tblId": "_KNCC_QS_CKUP",
            "colId": "CSCOPANR",
            "tblNm": "검사",
            "dispFormat": "텍스트"
        },
        {
            "gpId": "_KNCC_CKUP",
            "colDesc": "대장내시경처음검사",
            "num": 31,
            "dataType": "STRING",
            "colCnt": 45003,
            "gpNm": "검사",
            "colNm": "대장내시경처음검사",
            "tblId": "_KNCC_QS_CKUP",
            "colId": "CSCOPFY",
            "tblNm": "검사",
            "dispFormat": "YYYY, 모름=9999"
        },
        {
            "gpId": "_KNCC_CKUP",
            "colDesc": "대장내시경마지막검사",
            "num": 32,
            "dataType": "STRING",
            "colCnt": 45003,
            "gpNm": "검사",
            "colNm": "대장내시경마지막검사",
            "tblId": "_KNCC_QS_CKUP",
            "colId": "CSCOPLY",
            "tblNm": "검사",
            "dispFormat": "YYYY, 모름=9999"
        },
        {
            "gpId": "_KNCC_CKUP",
            "colDesc": "대장조영술",
            "num": 33,
            "dataType": "STRING",
            "colCnt": 45003,
            "gpNm": "검사",
            "colNm": "대장조영술",
            "tblId": "_KNCC_QS_CKUP",
            "colId": "COLON",
            "tblNm": "검사",
            "dispFormat": "1=있다"
        },
        {
            "gpId": "_KNCC_CKUP",
            "colDesc": "대장조영술검진이유_이상증상",
            "num": 34,
            "dataType": "STRING",
            "colCnt": 45003,
            "gpNm": "검사",
            "colNm": "대장조영술검진이유_이상증상",
            "tblId": "_KNCC_QS_CKUP",
            "colId": "COLONRE_1",
            "tblNm": "검사",
            "dispFormat": "값이 존재할 경우 이상증상"
        },
        {
            "gpId": "_KNCC_CKUP",
            "colDesc": "대장조영술검진이유_정기검진",
            "num": 35,
            "dataType": "STRING",
            "colCnt": 45003,
            "gpNm": "검사",
            "colNm": "대장조영술검진이유_정기검진",
            "tblId": "_KNCC_QS_CKUP",
            "colId": "COLONRE_2",
            "tblNm": "검사",
            "dispFormat": "값이 존재할 경우 정기검진"
        },
        {
            "gpId": "_KNCC_CKUP",
            "colDesc": "대장조영술받은횟수",
            "num": 36,
            "dataType": "STRING",
            "colCnt": 45003,
            "gpNm": "검사",
            "colNm": "대장조영술받은횟수",
            "tblId": "_KNCC_QS_CKUP",
            "colId": "COLONNUM",
            "tblNm": "검사",
            "dispFormat": "1-9, 모름=9999"
        },
        {
            "gpId": "_KNCC_CKUP",
            "colDesc": "대장조영술검사결과",
            "num": 37,
            "dataType": "STRING",
            "colCnt": 45003,
            "gpNm": "검사",
            "colNm": "대장조영술검사결과",
            "tblId": "_KNCC_QS_CKUP",
            "colId": "COLONNR",
            "tblNm": "검사",
            "dispFormat": "1=정상"
        },
        {
            "gpId": "_KNCC_CKUP",
            "colDesc": "대장조영술정상이외",
            "num": 38,
            "dataType": "STRING",
            "colCnt": 45003,
            "gpNm": "검사",
            "colNm": "대장조영술정상이외",
            "tblId": "_KNCC_QS_CKUP",
            "colId": "COLONANR",
            "tblNm": "검사",
            "dispFormat": "텍스트"
        },
        {
            "gpId": "_KNCC_CKUP",
            "colDesc": "대장조영술처음검사",
            "num": 39,
            "dataType": "STRING",
            "colCnt": 45003,
            "gpNm": "검사",
            "colNm": "대장조영술처음검사",
            "tblId": "_KNCC_QS_CKUP",
            "colId": "COLONFY",
            "tblNm": "검사",
            "dispFormat": "YYYY, 모름=9999"
        },
        {
            "gpId": "_KNCC_CKUP",
            "colDesc": "대장조영술마지막검사",
            "num": 40,
            "dataType": "STRING",
            "colCnt": 45003,
            "gpNm": "검사",
            "colNm": "대장조영술마지막검사",
            "tblId": "_KNCC_QS_CKUP",
            "colId": "COLONLY",
            "tblNm": "검사",
            "dispFormat": "YYYY, 모름=9999"
        },
        {
            "gpId": "_KNCC_CKUP",
            "colDesc": "대변잠혈검사",
            "num": 41,
            "dataType": "STRING",
            "colCnt": 45003,
            "gpNm": "검사",
            "colNm": "대변잠혈검사",
            "tblId": "_KNCC_QS_CKUP",
            "colId": "STOOL",
            "tblNm": "검사",
            "dispFormat": "1=있다"
        },
        {
            "gpId": "_KNCC_CKUP",
            "colDesc": "대변잠혈검사검진이유_이상증상",
            "num": 42,
            "dataType": "STRING",
            "colCnt": 45003,
            "gpNm": "검사",
            "colNm": "대변잠혈검사검진이유_이상증상",
            "tblId": "_KNCC_QS_CKUP",
            "colId": "STOOLRE_1",
            "tblNm": "검사",
            "dispFormat": "값이 존재할 경우 이상증상"
        },
        {
            "gpId": "_KNCC_CKUP",
            "colDesc": "대변잠혈검사검진이유_정기검진",
            "num": 43,
            "dataType": "STRING",
            "colCnt": 45003,
            "gpNm": "검사",
            "colNm": "대변잠혈검사검진이유_정기검진",
            "tblId": "_KNCC_QS_CKUP",
            "colId": "STOOLRE_2",
            "tblNm": "검사",
            "dispFormat": "값이 존재할 경우 정기검진"
        },
        {
            "gpId": "_KNCC_CKUP",
            "colDesc": "대변잠혈검사받은횟수",
            "num": 44,
            "dataType": "INTEGER",
            "colCnt": 4408,
            "gpNm": "검사",
            "colNm": "대변잠혈검사받은횟수",
            "tblId": "_KNCC_QS_CKUP",
            "colId": "STOOLNUM",
            "tblNm": "검사",
            "dispFormat": "1-9, 모름=9999"
        },
        {
            "gpId": "_KNCC_CKUP",
            "colDesc": "대변잠혈검사검사결과",
            "num": 45,
            "dataType": "STRING",
            "colCnt": 45003,
            "gpNm": "검사",
            "colNm": "대변잠혈검사검사결과",
            "tblId": "_KNCC_QS_CKUP",
            "colId": "STOOLNR",
            "tblNm": "검사",
            "dispFormat": "1=정상"
        },
        {
            "gpId": "_KNCC_CKUP",
            "colDesc": "대변잠혈검사정상이외의",
            "num": 46,
            "dataType": "STRING",
            "colCnt": 45003,
            "gpNm": "검사",
            "colNm": "대변잠혈검사정상이외의",
            "tblId": "_KNCC_QS_CKUP",
            "colId": "STOOLANR",
            "tblNm": "검사",
            "dispFormat": "텍스트"
        },
        {
            "gpId": "_KNCC_CKUP",
            "colDesc": "대변잠혈검사처음검사",
            "num": 47,
            "dataType": "STRING",
            "colCnt": 45003,
            "gpNm": "검사",
            "colNm": "대변잠혈검사처음검사",
            "tblId": "_KNCC_QS_CKUP",
            "colId": "STOOLFY",
            "tblNm": "검사",
            "dispFormat": "YYYY, 모름=9999"
        },
        {
            "gpId": "_KNCC_CKUP",
            "colDesc": "대변잠혈검사마지막검사",
            "num": 48,
            "dataType": "STRING",
            "colCnt": 45003,
            "gpNm": "검사",
            "colNm": "대변잠혈검사마지막검사",
            "tblId": "_KNCC_QS_CKUP",
            "colId": "STOOLLY",
            "tblNm": "검사",
            "dispFormat": "YYYY, 모름=9999"
        },
        {
            "gpId": "_KNCC_CKUP",
            "colDesc": "복부초음파",
            "num": 49,
            "dataType": "STRING",
            "colCnt": 45003,
            "gpNm": "검사",
            "colNm": "복부초음파",
            "tblId": "_KNCC_QS_CKUP",
            "colId": "ABSN",
            "tblNm": "검사",
            "dispFormat": "1=있다"
        },
        {
            "gpId": "_KNCC_CKUP",
            "colDesc": "복부초음파검진이유_이상증상",
            "num": 50,
            "dataType": "STRING",
            "colCnt": 45003,
            "gpNm": "검사",
            "colNm": "복부초음파검진이유_이상증상",
            "tblId": "_KNCC_QS_CKUP",
            "colId": "ABSNRE_1",
            "tblNm": "검사",
            "dispFormat": "값이 존재할 경우 이상증상"
        },
        {
            "gpId": "_KNCC_CKUP",
            "colDesc": "복부초음파검진이유_정기검진",
            "num": 51,
            "dataType": "STRING",
            "colCnt": 45003,
            "gpNm": "검사",
            "colNm": "복부초음파검진이유_정기검진",
            "tblId": "_KNCC_QS_CKUP",
            "colId": "ABSNRE_2",
            "tblNm": "검사",
            "dispFormat": "값이 존재할 경우 정기검진"
        },
        {
            "gpId": "_KNCC_CKUP",
            "colDesc": "복부초음파받은횟수",
            "num": 52,
            "dataType": "INTEGER",
            "colCnt": 6608,
            "gpNm": "검사",
            "colNm": "복부초음파받은횟수",
            "tblId": "_KNCC_QS_CKUP",
            "colId": "ABSNNUM",
            "tblNm": "검사",
            "dispFormat": "1-9, 모름=9999"
        },
        {
            "gpId": "_KNCC_CKUP",
            "colDesc": "복부초음파검사결과",
            "num": 53,
            "dataType": "STRING",
            "colCnt": 45003,
            "gpNm": "검사",
            "colNm": "복부초음파검사결과",
            "tblId": "_KNCC_QS_CKUP",
            "colId": "ABSNNR",
            "tblNm": "검사",
            "dispFormat": "1=정상"
        },
        {
            "gpId": "_KNCC_CKUP",
            "colDesc": "복부초음파정상이외",
            "num": 54,
            "dataType": "STRING",
            "colCnt": 45003,
            "gpNm": "검사",
            "colNm": "복부초음파정상이외",
            "tblId": "_KNCC_QS_CKUP",
            "colId": "ABSNANR",
            "tblNm": "검사",
            "dispFormat": "텍스트"
        },
        {
            "gpId": "_KNCC_CKUP",
            "colDesc": "복부초음파처음검사",
            "num": 55,
            "dataType": "STRING",
            "colCnt": 45003,
            "gpNm": "검사",
            "colNm": "복부초음파처음검사",
            "tblId": "_KNCC_QS_CKUP",
            "colId": "ABSNFY",
            "tblNm": "검사",
            "dispFormat": "YYYY, 모름=9999"
        },
        {
            "gpId": "_KNCC_CKUP",
            "colDesc": "복부초음파마지막검사",
            "num": 56,
            "dataType": "STRING",
            "colCnt": 45003,
            "gpNm": "검사",
            "colNm": "복부초음파마지막검사",
            "tblId": "_KNCC_QS_CKUP",
            "colId": "ABSNLY",
            "tblNm": "검사",
            "dispFormat": "YYYY, 모름=9999"
        },
        {
            "gpId": "_KNCC_CKUP",
            "colDesc": "알파태아단백검사",
            "num": 57,
            "dataType": "STRING",
            "colCnt": 45003,
            "gpNm": "검사",
            "colNm": "알파태아단백검사",
            "tblId": "_KNCC_QS_CKUP",
            "colId": "AFP",
            "tblNm": "검사",
            "dispFormat": "1=있다"
        },
        {
            "gpId": "_KNCC_CKUP",
            "colDesc": "알파태아단백검사검진이유_이상증상",
            "num": 58,
            "dataType": "STRING",
            "colCnt": 45003,
            "gpNm": "검사",
            "colNm": "알파태아단백검사검진이유_이상증상",
            "tblId": "_KNCC_QS_CKUP",
            "colId": "AFPRE_1",
            "tblNm": "검사",
            "dispFormat": "값이 존재할 경우 이상증상"
        },
        {
            "gpId": "_KNCC_CKUP",
            "colDesc": "알파태아단백검사검진이유_정기검진",
            "num": 59,
            "dataType": "STRING",
            "colCnt": 45003,
            "gpNm": "검사",
            "colNm": "알파태아단백검사검진이유_정기검진",
            "tblId": "_KNCC_QS_CKUP",
            "colId": "AFPRE_2",
            "tblNm": "검사",
            "dispFormat": "값이 존재할 경우 정기검진"
        },
        {
            "gpId": "_KNCC_CKUP",
            "colDesc": "알파태아단백검사받은횟수",
            "num": 60,
            "dataType": "STRING",
            "colCnt": 45003,
            "gpNm": "검사",
            "colNm": "알파태아단백검사받은횟수",
            "tblId": "_KNCC_QS_CKUP",
            "colId": "AFPNUM",
            "tblNm": "검사",
            "dispFormat": "1-9, 모름=9999"
        },
        {
            "gpId": "_KNCC_CKUP",
            "colDesc": "알파태아단백검사검사결과",
            "num": 61,
            "dataType": "STRING",
            "colCnt": 45003,
            "gpNm": "검사",
            "colNm": "알파태아단백검사검사결과",
            "tblId": "_KNCC_QS_CKUP",
            "colId": "AFPNR",
            "tblNm": "검사",
            "dispFormat": "1=정상"
        },
        {
            "gpId": "_KNCC_CKUP",
            "colDesc": "알파태아단백검사정상이외",
            "num": 62,
            "dataType": "STRING",
            "colCnt": 45003,
            "gpNm": "검사",
            "colNm": "알파태아단백검사정상이외",
            "tblId": "_KNCC_QS_CKUP",
            "colId": "AFPANR",
            "tblNm": "검사",
            "dispFormat": "텍스트"
        },
        {
            "gpId": "_KNCC_CKUP",
            "colDesc": "알파태아단백검사처음검사",
            "num": 63,
            "dataType": "STRING",
            "colCnt": 45003,
            "gpNm": "검사",
            "colNm": "알파태아단백검사처음검사",
            "tblId": "_KNCC_QS_CKUP",
            "colId": "AFPFY",
            "tblNm": "검사",
            "dispFormat": "YYYY, 모름=9999"
        },
        {
            "gpId": "_KNCC_CKUP",
            "colDesc": "알파태아단백검사마지막검사",
            "num": 64,
            "dataType": "STRING",
            "colCnt": 45003,
            "gpNm": "검사",
            "colNm": "알파태아단백검사마지막검사",
            "tblId": "_KNCC_QS_CKUP",
            "colId": "AFPLY",
            "tblNm": "검사",
            "dispFormat": "YYYY, 모름=9999"
        },
        {
            "gpId": "_KNCC_CKUP",
            "colDesc": "전립선특이항원(PSA)",
            "num": 65,
            "dataType": "STRING",
            "colCnt": 45003,
            "gpNm": "검사",
            "colNm": "전립선특이항원(PSA)",
            "tblId": "_KNCC_QS_CKUP",
            "colId": "PSA",
            "tblNm": "검사",
            "dispFormat": "1=있다"
        },
        {
            "gpId": "_KNCC_CKUP",
            "colDesc": "전립선특이항원(PSA)검진이유_이상증상",
            "num": 66,
            "dataType": "STRING",
            "colCnt": 45003,
            "gpNm": "검사",
            "colNm": "전립선특이항원(PSA)검진이유_이상증상",
            "tblId": "_KNCC_QS_CKUP",
            "colId": "PSARE_1",
            "tblNm": "검사",
            "dispFormat": "값이 존재할 경우 이상증상"
        },
        {
            "gpId": "_KNCC_CKUP",
            "colDesc": "전립선특이항원(PSA)검진이유_정기검진",
            "num": 67,
            "dataType": "STRING",
            "colCnt": 45003,
            "gpNm": "검사",
            "colNm": "전립선특이항원(PSA)검진이유_정기검진",
            "tblId": "_KNCC_QS_CKUP",
            "colId": "PSARE_2",
            "tblNm": "검사",
            "dispFormat": "값이 존재할 경우 정기검진"
        },
        {
            "gpId": "_KNCC_CKUP",
            "colDesc": "전립선특이항원(PSA)받은횟수",
            "num": 68,
            "dataType": "INTEGER",
            "colCnt": 10449,
            "gpNm": "검사",
            "colNm": "전립선특이항원(PSA)받은횟수",
            "tblId": "_KNCC_QS_CKUP",
            "colId": "PSANUM",
            "tblNm": "검사",
            "dispFormat": "1-9, 모름=9999"
        },
        {
            "gpId": "_KNCC_CKUP",
            "colDesc": "전립선특이항원(PSA)검사결과",
            "num": 69,
            "dataType": "STRING",
            "colCnt": 45003,
            "gpNm": "검사",
            "colNm": "전립선특이항원(PSA)검사결과",
            "tblId": "_KNCC_QS_CKUP",
            "colId": "PSANR",
            "tblNm": "검사",
            "dispFormat": "1=정상"
        },
        {
            "gpId": "_KNCC_CKUP",
            "colDesc": "전립선특이항원(PSA)정상이외",
            "num": 70,
            "dataType": "STRING",
            "colCnt": 45003,
            "gpNm": "검사",
            "colNm": "전립선특이항원(PSA)정상이외",
            "tblId": "_KNCC_QS_CKUP",
            "colId": "PSAANR",
            "tblNm": "검사",
            "dispFormat": "텍스트"
        },
        {
            "gpId": "_KNCC_CKUP",
            "colDesc": "전립선특이항원(PSA)처음검사",
            "num": 71,
            "dataType": "STRING",
            "colCnt": 45003,
            "gpNm": "검사",
            "colNm": "전립선특이항원(PSA)처음검사",
            "tblId": "_KNCC_QS_CKUP",
            "colId": "PSAFY",
            "tblNm": "검사",
            "dispFormat": "YYYY, 모름=9999"
        },
        {
            "gpId": "_KNCC_CKUP",
            "colDesc": "전립선특이항원(PSA)마지막검사",
            "num": 72,
            "dataType": "STRING",
            "colCnt": 45003,
            "gpNm": "검사",
            "colNm": "전립선특이항원(PSA)마지막검사",
            "tblId": "_KNCC_QS_CKUP",
            "colId": "PSALY",
            "tblNm": "검사",
            "dispFormat": "YYYY, 모름=9999"
        },
        {
            "gpId": "_KNCC_CKUP",
            "colDesc": "유방진찰",
            "num": 73,
            "dataType": "STRING",
            "colCnt": 45003,
            "gpNm": "검사",
            "colNm": "유방진찰",
            "tblId": "_KNCC_QS_CKUP",
            "colId": "BRSC",
            "tblNm": "검사",
            "dispFormat": "1=있다"
        },
        {
            "gpId": "_KNCC_CKUP",
            "colDesc": "유방진찰검진이유_이상증상",
            "num": 74,
            "dataType": "STRING",
            "colCnt": 45003,
            "gpNm": "검사",
            "colNm": "유방진찰검진이유_이상증상",
            "tblId": "_KNCC_QS_CKUP",
            "colId": "BRSCRE_1",
            "tblNm": "검사",
            "dispFormat": "값이 존재할 경우 이상증상"
        },
        {
            "gpId": "_KNCC_CKUP",
            "colDesc": "유방진찰검진이유_정기검진",
            "num": 75,
            "dataType": "STRING",
            "colCnt": 45003,
            "gpNm": "검사",
            "colNm": "유방진찰검진이유_정기검진",
            "tblId": "_KNCC_QS_CKUP",
            "colId": "BRSCRE_2",
            "tblNm": "검사",
            "dispFormat": "값이 존재할 경우 정기검진"
        },
        {
            "gpId": "_KNCC_CKUP",
            "colDesc": "유방진찰받은횟수",
            "num": 76,
            "dataType": "INTEGER",
            "colCnt": 19588,
            "gpNm": "검사",
            "colNm": "유방진찰받은횟수",
            "tblId": "_KNCC_QS_CKUP",
            "colId": "BRSCNUM",
            "tblNm": "검사",
            "dispFormat": "1-9, 모름=9999"
        },
        {
            "gpId": "_KNCC_CKUP",
            "colDesc": "유방진찰검사결과",
            "num": 77,
            "dataType": "STRING",
            "colCnt": 45003,
            "gpNm": "검사",
            "colNm": "유방진찰검사결과",
            "tblId": "_KNCC_QS_CKUP",
            "colId": "BRSCNR",
            "tblNm": "검사",
            "dispFormat": "1=정상"
        },
        {
            "gpId": "_KNCC_CKUP",
            "colDesc": "유방진찰정상이외",
            "num": 78,
            "dataType": "STRING",
            "colCnt": 45003,
            "gpNm": "검사",
            "colNm": "유방진찰정상이외",
            "tblId": "_KNCC_QS_CKUP",
            "colId": "BRSCANR",
            "tblNm": "검사",
            "dispFormat": "텍스트"
        },
        {
            "gpId": "_KNCC_CKUP",
            "colDesc": "유방진찰처음검사",
            "num": 79,
            "dataType": "STRING",
            "colCnt": 45003,
            "gpNm": "검사",
            "colNm": "유방진찰처음검사",
            "tblId": "_KNCC_QS_CKUP",
            "colId": "BRSCFY",
            "tblNm": "검사",
            "dispFormat": "YYYY, 모름=9999"
        },
        {
            "gpId": "_KNCC_CKUP",
            "colDesc": "유방진찰마지막검사",
            "num": 80,
            "dataType": "STRING",
            "colCnt": 45003,
            "gpNm": "검사",
            "colNm": "유방진찰마지막검사",
            "tblId": "_KNCC_QS_CKUP",
            "colId": "BRSCLY",
            "tblNm": "검사",
            "dispFormat": "YYYY, 모름=9999"
        },
        {
            "gpId": "_KNCC_CKUP",
            "colDesc": "유방촬영술",
            "num": 81,
            "dataType": "STRING",
            "colCnt": 45003,
            "gpNm": "검사",
            "colNm": "유방촬영술",
            "tblId": "_KNCC_QS_CKUP",
            "colId": "MAMMO",
            "tblNm": "검사",
            "dispFormat": "1=있다"
        },
        {
            "gpId": "_KNCC_CKUP",
            "colDesc": "유방촬영술검진이유_이상증상",
            "num": 82,
            "dataType": "STRING",
            "colCnt": 45003,
            "gpNm": "검사",
            "colNm": "유방촬영술검진이유_이상증상",
            "tblId": "_KNCC_QS_CKUP",
            "colId": "MAMRE_1",
            "tblNm": "검사",
            "dispFormat": "값이 존재할 경우 이상증상"
        },
        {
            "gpId": "_KNCC_CKUP",
            "colDesc": "유방촬영술검진이유_정기검진",
            "num": 83,
            "dataType": "STRING",
            "colCnt": 45003,
            "gpNm": "검사",
            "colNm": "유방촬영술검진이유_정기검진",
            "tblId": "_KNCC_QS_CKUP",
            "colId": "MAMRE_2",
            "tblNm": "검사",
            "dispFormat": "값이 존재할 경우 정기검진"
        },
        {
            "gpId": "_KNCC_CKUP",
            "colDesc": "유방촬영술받은횟수",
            "num": 84,
            "dataType": "INTEGER",
            "colCnt": 6718,
            "gpNm": "검사",
            "colNm": "유방촬영술받은횟수",
            "tblId": "_KNCC_QS_CKUP",
            "colId": "MAMNUM",
            "tblNm": "검사",
            "dispFormat": "1-9, 모름=9999"
        },
        {
            "gpId": "_KNCC_CKUP",
            "colDesc": "유방촬영술검사결과",
            "num": 85,
            "dataType": "STRING",
            "colCnt": 45003,
            "gpNm": "검사",
            "colNm": "유방촬영술검사결과",
            "tblId": "_KNCC_QS_CKUP",
            "colId": "MAMNR",
            "tblNm": "검사",
            "dispFormat": "1=정상"
        },
        {
            "gpId": "_KNCC_CKUP",
            "colDesc": "유방촬영술정상이외",
            "num": 86,
            "dataType": "STRING",
            "colCnt": 45003,
            "gpNm": "검사",
            "colNm": "유방촬영술정상이외",
            "tblId": "_KNCC_QS_CKUP",
            "colId": "MAMANR",
            "tblNm": "검사",
            "dispFormat": "텍스트"
        },
        {
            "gpId": "_KNCC_CKUP",
            "colDesc": "유방촬영술처음검사",
            "num": 87,
            "dataType": "STRING",
            "colCnt": 45003,
            "gpNm": "검사",
            "colNm": "유방촬영술처음검사",
            "tblId": "_KNCC_QS_CKUP",
            "colId": "MAMFY",
            "tblNm": "검사",
            "dispFormat": "YYYY, 모름=9999"
        },
        {
            "gpId": "_KNCC_CKUP",
            "colDesc": "유방촬영술마지막검사",
            "num": 88,
            "dataType": "STRING",
            "colCnt": 45003,
            "gpNm": "검사",
            "colNm": "유방촬영술마지막검사",
            "tblId": "_KNCC_QS_CKUP",
            "colId": "MAMLY",
            "tblNm": "검사",
            "dispFormat": "YYYY, 모름=9999"
        },
        {
            "gpId": "_KNCC_CKUP",
            "colDesc": "유방초음파_설문",
            "num": 89,
            "dataType": "STRING",
            "colCnt": 45003,
            "gpNm": "검사",
            "colNm": "유방초음파_설문",
            "tblId": "_KNCC_QS_CKUP",
            "colId": "BRSN",
            "tblNm": "검사",
            "dispFormat": "1=있다"
        },
        {
            "gpId": "_KNCC_CKUP",
            "colDesc": "유방초음파검진이유_이상증상",
            "num": 90,
            "dataType": "STRING",
            "colCnt": 45003,
            "gpNm": "검사",
            "colNm": "유방초음파검진이유_이상증상",
            "tblId": "_KNCC_QS_CKUP",
            "colId": "BRSNRE_1",
            "tblNm": "검사",
            "dispFormat": "값이 존재할 경우 이상증상"
        },
        {
            "gpId": "_KNCC_CKUP",
            "colDesc": "유방초음파검진이유_정기검진",
            "num": 91,
            "dataType": "STRING",
            "colCnt": 45003,
            "gpNm": "검사",
            "colNm": "유방초음파검진이유_정기검진",
            "tblId": "_KNCC_QS_CKUP",
            "colId": "BRSNRE_2",
            "tblNm": "검사",
            "dispFormat": "값이 존재할 경우 정기검진"
        },
        {
            "gpId": "_KNCC_CKUP",
            "colDesc": "유방초음파받은횟수",
            "num": 92,
            "dataType": "INTEGER",
            "colCnt": 18411,
            "gpNm": "검사",
            "colNm": "유방초음파받은횟수",
            "tblId": "_KNCC_QS_CKUP",
            "colId": "BRSNNUM",
            "tblNm": "검사",
            "dispFormat": "1-9, 모름=9999"
        },
        {
            "gpId": "_KNCC_CKUP",
            "colDesc": "유방초음파검사결과",
            "num": 93,
            "dataType": "STRING",
            "colCnt": 45003,
            "gpNm": "검사",
            "colNm": "유방초음파검사결과",
            "tblId": "_KNCC_QS_CKUP",
            "colId": "BRSNNR",
            "tblNm": "검사",
            "dispFormat": "1=정상"
        },
        {
            "gpId": "_KNCC_CKUP",
            "colDesc": "유방초음파정상이외",
            "num": 94,
            "dataType": "STRING",
            "colCnt": 45003,
            "gpNm": "검사",
            "colNm": "유방초음파정상이외",
            "tblId": "_KNCC_QS_CKUP",
            "colId": "BRSNANR",
            "tblNm": "검사",
            "dispFormat": "텍스트"
        },
        {
            "gpId": "_KNCC_CKUP",
            "colDesc": "유방초음파처음검사",
            "num": 95,
            "dataType": "STRING",
            "colCnt": 45003,
            "gpNm": "검사",
            "colNm": "유방초음파처음검사",
            "tblId": "_KNCC_QS_CKUP",
            "colId": "BRSNFY",
            "tblNm": "검사",
            "dispFormat": "YYYY, 모름=9999"
        },
        {
            "gpId": "_KNCC_CKUP",
            "colDesc": "유방초음파마지막검사",
            "num": 96,
            "dataType": "STRING",
            "colCnt": 45003,
            "gpNm": "검사",
            "colNm": "유방초음파마지막검사",
            "tblId": "_KNCC_QS_CKUP",
            "colId": "BRSNLY",
            "tblNm": "검사",
            "dispFormat": "YYYY, 모름=9999"
        },
        {
            "gpId": "_KNCC_CKUP",
            "colDesc": "자궁경부암검사",
            "num": 97,
            "dataType": "STRING",
            "colCnt": 45003,
            "gpNm": "검사",
            "colNm": "자궁경부암검사",
            "tblId": "_KNCC_QS_CKUP",
            "colId": "PAPS",
            "tblNm": "검사",
            "dispFormat": "1=있다"
        },
        {
            "gpId": "_KNCC_CKUP",
            "colDesc": "자궁경부암검사검진이유_이상증상",
            "num": 98,
            "dataType": "STRING",
            "colCnt": 45003,
            "gpNm": "검사",
            "colNm": "자궁경부암검사검진이유_이상증상",
            "tblId": "_KNCC_QS_CKUP",
            "colId": "PAPSRE_1",
            "tblNm": "검사",
            "dispFormat": "값이 존재할 경우 이상증상"
        },
        {
            "gpId": "_KNCC_CKUP",
            "colDesc": "자궁경부암검사검진이유_정기검진",
            "num": 99,
            "dataType": "STRING",
            "colCnt": 45003,
            "gpNm": "검사",
            "colNm": "자궁경부암검사검진이유_정기검진",
            "tblId": "_KNCC_QS_CKUP",
            "colId": "PAPSRE_2",
            "tblNm": "검사",
            "dispFormat": "값이 존재할 경우 정기검진"
        },
        {
            "gpId": "_KNCC_CKUP",
            "colDesc": "자궁경부암검사받은횟수",
            "num": 100,
            "dataType": "INTEGER",
            "colCnt": 7269,
            "gpNm": "검사",
            "colNm": "자궁경부암검사받은횟수",
            "tblId": "_KNCC_QS_CKUP",
            "colId": "PAPSNUM",
            "tblNm": "검사",
            "dispFormat": "1-9, 모름=9999"
        },
        {
            "gpId": "_KNCC_CKUP",
            "colDesc": "자궁경부암검사검사결과",
            "num": 101,
            "dataType": "STRING",
            "colCnt": 45003,
            "gpNm": "검사",
            "colNm": "자궁경부암검사검사결과",
            "tblId": "_KNCC_QS_CKUP",
            "colId": "PAPSNR",
            "tblNm": "검사",
            "dispFormat": "1=정상"
        },
        {
            "gpId": "_KNCC_CKUP",
            "colDesc": "자궁경부암검사정상이외",
            "num": 102,
            "dataType": "STRING",
            "colCnt": 45003,
            "gpNm": "검사",
            "colNm": "자궁경부암검사정상이외",
            "tblId": "_KNCC_QS_CKUP",
            "colId": "PAPSANR",
            "tblNm": "검사",
            "dispFormat": "텍스트"
        },
        {
            "gpId": "_KNCC_CKUP",
            "colDesc": "자궁경부암검사처음검사",
            "num": 103,
            "dataType": "STRING",
            "colCnt": 45003,
            "gpNm": "검사",
            "colNm": "자궁경부암검사처음검사",
            "tblId": "_KNCC_QS_CKUP",
            "colId": "PAPSFY",
            "tblNm": "검사",
            "dispFormat": "YYYY, 모름=9999"
        },
        {
            "gpId": "_KNCC_CKUP",
            "colDesc": "자궁경부암검사마지막검사",
            "num": 104,
            "dataType": "STRING",
            "colCnt": 45003,
            "gpNm": "검사",
            "colNm": "자궁경부암검사마지막검사",
            "tblId": "_KNCC_QS_CKUP",
            "colId": "PAPSLY",
            "tblNm": "검사",
            "dispFormat": "YYYY, 모름=9999"
        },
        {
            "gpId": "_KNCC_CKUP",
            "colDesc": "직장진찰",
            "num": 105,
            "dataType": "STRING",
            "colCnt": 45003,
            "gpNm": "검사",
            "colNm": "직장진찰",
            "tblId": "_KNCC_QS_CKUP",
            "colId": "RECT",
            "tblNm": "검사",
            "dispFormat": "1=있다"
        },
        {
            "gpId": "_KNCC_CKUP",
            "colDesc": "직장진찰검진이유_이상증상",
            "num": 106,
            "dataType": "STRING",
            "colCnt": 45003,
            "gpNm": "검사",
            "colNm": "직장진찰검진이유_이상증상",
            "tblId": "_KNCC_QS_CKUP",
            "colId": "RECTRE_1",
            "tblNm": "검사",
            "dispFormat": "값이 존재할 경우 이상증상"
        },
        {
            "gpId": "_KNCC_CKUP",
            "colDesc": "직장진찰검진이유_정기검진",
            "num": 107,
            "dataType": "STRING",
            "colCnt": 45003,
            "gpNm": "검사",
            "colNm": "직장진찰검진이유_정기검진",
            "tblId": "_KNCC_QS_CKUP",
            "colId": "RECTRE_2",
            "tblNm": "검사",
            "dispFormat": "값이 존재할 경우 정기검진"
        },
        {
            "gpId": "_KNCC_CKUP",
            "colDesc": "직장진찰받은횟수",
            "num": 108,
            "dataType": "INTEGER",
            "colCnt": 781,
            "gpNm": "검사",
            "colNm": "직장진찰받은횟수",
            "tblId": "_KNCC_QS_CKUP",
            "colId": "RECTNUM",
            "tblNm": "검사",
            "dispFormat": "1-9, 모름=9999"
        },
        {
            "gpId": "_KNCC_CKUP",
            "colDesc": "직장진찰검사결과",
            "num": 109,
            "dataType": "STRING",
            "colCnt": 45003,
            "gpNm": "검사",
            "colNm": "직장진찰검사결과",
            "tblId": "_KNCC_QS_CKUP",
            "colId": "RECTNR",
            "tblNm": "검사",
            "dispFormat": "1=정상"
        },
        {
            "gpId": "_KNCC_CKUP",
            "colDesc": "직장진찰정상이외",
            "num": 110,
            "dataType": "STRING",
            "colCnt": 45003,
            "gpNm": "검사",
            "colNm": "직장진찰정상이외",
            "tblId": "_KNCC_QS_CKUP",
            "colId": "RECTANR",
            "tblNm": "검사",
            "dispFormat": "텍스트"
        },
        {
            "gpId": "_KNCC_CKUP",
            "colDesc": "직장진찰처음검사",
            "num": 111,
            "dataType": "STRING",
            "colCnt": 45003,
            "gpNm": "검사",
            "colNm": "직장진찰처음검사",
            "tblId": "_KNCC_QS_CKUP",
            "colId": "RECTFY",
            "tblNm": "검사",
            "dispFormat": "YYYY, 모름=9999"
        },
        {
            "gpId": "_KNCC_CKUP",
            "colDesc": "직장진찰마지막검사",
            "num": 112,
            "dataType": "STRING",
            "colCnt": 45003,
            "gpNm": "검사",
            "colNm": "직장진찰마지막검사",
            "tblId": "_KNCC_QS_CKUP",
            "colId": "RECTLY",
            "tblNm": "검사",
            "dispFormat": "YYYY, 모름=9999"
        },
        {
            "gpId": "_KNCC_CKUP",
            "colDesc": "전립선생검검",
            "num": 113,
            "dataType": "STRING",
            "colCnt": 45003,
            "gpNm": "검사",
            "colNm": "전립선생검검",
            "tblId": "_KNCC_QS_CKUP",
            "colId": "PBX",
            "tblNm": "검사",
            "dispFormat": "1=있다"
        },
        {
            "gpId": "_KNCC_CKUP",
            "colDesc": "전립선생검검검진이유_이상증상",
            "num": 114,
            "dataType": "STRING",
            "colCnt": 45003,
            "gpNm": "검사",
            "colNm": "전립선생검검검진이유_이상증상",
            "tblId": "_KNCC_QS_CKUP",
            "colId": "PBXRE_1",
            "tblNm": "검사",
            "dispFormat": "값이 존재할 경우 이상증상"
        },
        {
            "gpId": "_KNCC_CKUP",
            "colDesc": "전립선생검검검진이유_정기검진",
            "num": 115,
            "dataType": "STRING",
            "colCnt": 45003,
            "gpNm": "검사",
            "colNm": "전립선생검검검진이유_정기검진",
            "tblId": "_KNCC_QS_CKUP",
            "colId": "PBXRE_2",
            "tblNm": "검사",
            "dispFormat": "값이 존재할 경우 정기검진"
        },
        {
            "gpId": "_KNCC_CKUP",
            "colDesc": "전립선생검검받은횟수",
            "num": 116,
            "dataType": "STRING",
            "colCnt": 45003,
            "gpNm": "검사",
            "colNm": "전립선생검검받은횟수",
            "tblId": "_KNCC_QS_CKUP",
            "colId": "PBXNUM",
            "tblNm": "검사",
            "dispFormat": "1-9, 모름=9999"
        },
        {
            "gpId": "_KNCC_CKUP",
            "colDesc": "전립선생검검검사결과",
            "num": 117,
            "dataType": "STRING",
            "colCnt": 45003,
            "gpNm": "검사",
            "colNm": "전립선생검검검사결과",
            "tblId": "_KNCC_QS_CKUP",
            "colId": "PBXNR",
            "tblNm": "검사",
            "dispFormat": "1=정상"
        },
        {
            "gpId": "_KNCC_CKUP",
            "colDesc": "전립선생검검정상이외",
            "num": 118,
            "dataType": "STRING",
            "colCnt": 45003,
            "gpNm": "검사",
            "colNm": "전립선생검검정상이외",
            "tblId": "_KNCC_QS_CKUP",
            "colId": "PBXANR",
            "tblNm": "검사",
            "dispFormat": "텍스트"
        },
        {
            "gpId": "_KNCC_CKUP",
            "colDesc": "전립선생검검처음검사",
            "num": 119,
            "dataType": "STRING",
            "colCnt": 45003,
            "gpNm": "검사",
            "colNm": "전립선생검검처음검사",
            "tblId": "_KNCC_QS_CKUP",
            "colId": "PBXFY",
            "tblNm": "검사",
            "dispFormat": "YYYY, 모름=9999"
        },
        {
            "gpId": "_KNCC_CKUP",
            "colDesc": "전립선생검검마지막검사",
            "num": 120,
            "dataType": "STRING",
            "colCnt": 45003,
            "gpNm": "검사",
            "colNm": "전립선생검검마지막검사",
            "tblId": "_KNCC_QS_CKUP",
            "colId": "PBXLY",
            "tblNm": "검사",
            "dispFormat": "YYYY, 모름=9999"
        },
        {
            "gpId": "_KNCC_CKUP",
            "colDesc": "전산화단층촬영(CT)",
            "num": 121,
            "dataType": "STRING",
            "colCnt": 45003,
            "gpNm": "검사",
            "colNm": "전산화단층촬영(CT)",
            "tblId": "_KNCC_QS_CKUP",
            "colId": "CT",
            "tblNm": "검사",
            "dispFormat": "1=있다"
        },
        {
            "gpId": "_KNCC_CKUP",
            "colDesc": "전산화단층촬영(CT)검진이유_이상증상",
            "num": 122,
            "dataType": "STRING",
            "colCnt": 45003,
            "gpNm": "검사",
            "colNm": "전산화단층촬영(CT)검진이유_이상증상",
            "tblId": "_KNCC_QS_CKUP",
            "colId": "CTRE_1",
            "tblNm": "검사",
            "dispFormat": "값이 존재할 경우 이상증상"
        },
        {
            "gpId": "_KNCC_CKUP",
            "colDesc": "전산화단층촬영(CT)검진이유_정기검진",
            "num": 123,
            "dataType": "STRING",
            "colCnt": 45003,
            "gpNm": "검사",
            "colNm": "전산화단층촬영(CT)검진이유_정기검진",
            "tblId": "_KNCC_QS_CKUP",
            "colId": "CTRE_2",
            "tblNm": "검사",
            "dispFormat": "값이 존재할 경우 정기검진"
        },
        {
            "gpId": "_KNCC_CKUP",
            "colDesc": "전산화단층촬영(CT)받은횟수",
            "num": 124,
            "dataType": "INTEGER",
            "colCnt": 3938,
            "gpNm": "검사",
            "colNm": "전산화단층촬영(CT)받은횟수",
            "tblId": "_KNCC_QS_CKUP",
            "colId": "CTNUM",
            "tblNm": "검사",
            "dispFormat": "1-9, 모름=9999"
        },
        {
            "gpId": "_KNCC_CKUP",
            "colDesc": "전산화단층촬영(CT)검사결과",
            "num": 125,
            "dataType": "STRING",
            "colCnt": 45003,
            "gpNm": "검사",
            "colNm": "전산화단층촬영(CT)검사결과",
            "tblId": "_KNCC_QS_CKUP",
            "colId": "CTNR",
            "tblNm": "검사",
            "dispFormat": "1=정상"
        },
        {
            "gpId": "_KNCC_CKUP",
            "colDesc": "전산화단층촬영(CT)정상이외",
            "num": 126,
            "dataType": "STRING",
            "colCnt": 45003,
            "gpNm": "검사",
            "colNm": "전산화단층촬영(CT)정상이외",
            "tblId": "_KNCC_QS_CKUP",
            "colId": "CTANR",
            "tblNm": "검사",
            "dispFormat": "텍스트"
        },
        {
            "gpId": "_KNCC_CKUP",
            "colDesc": "전산화단층촬영(CT)촬영부위",
            "num": 127,
            "dataType": "STRING",
            "colCnt": 45003,
            "gpNm": "검사",
            "colNm": "전산화단층촬영(CT)촬영부위",
            "tblId": "_KNCC_QS_CKUP",
            "colId": "CTST",
            "tblNm": "검사",
            "dispFormat": "텍스트"
        },
        {
            "gpId": "_KNCC_CKUP",
            "colDesc": "전산화단층촬영(CT)처음검사",
            "num": 128,
            "dataType": "STRING",
            "colCnt": 45003,
            "gpNm": "검사",
            "colNm": "전산화단층촬영(CT)처음검사",
            "tblId": "_KNCC_QS_CKUP",
            "colId": "CTFY",
            "tblNm": "검사",
            "dispFormat": "YYYY, 모름=9999"
        },
        {
            "gpId": "_KNCC_CKUP",
            "colDesc": "전산화단층촬영(CT)마지막검사",
            "num": 129,
            "dataType": "STRING",
            "colCnt": 45003,
            "gpNm": "검사",
            "colNm": "전산화단층촬영(CT)마지막검사",
            "tblId": "_KNCC_QS_CKUP",
            "colId": "CTLY",
            "tblNm": "검사",
            "dispFormat": "YYYY, 모름=9999"
        },
        {
            "gpId": "_KNCC_CKUP",
            "colDesc": "자기공명영상촬영(MRI)",
            "num": 130,
            "dataType": "STRING",
            "colCnt": 45003,
            "gpNm": "검사",
            "colNm": "자기공명영상촬영(MRI)",
            "tblId": "_KNCC_QS_CKUP",
            "colId": "MRI",
            "tblNm": "검사",
            "dispFormat": "1=있다"
        },
        {
            "gpId": "_KNCC_CKUP",
            "colDesc": "자기공명영상촬영(MRI)검진이유_이상증상",
            "num": 131,
            "dataType": "STRING",
            "colCnt": 45003,
            "gpNm": "검사",
            "colNm": "자기공명영상촬영(MRI)검진이유_이상증상",
            "tblId": "_KNCC_QS_CKUP",
            "colId": "MRIRE_1",
            "tblNm": "검사",
            "dispFormat": "값이 존재할 경우 이상증상"
        },
        {
            "gpId": "_KNCC_CKUP",
            "colDesc": "자기공명영상촬영(MRI)검진이유_정기검진",
            "num": 132,
            "dataType": "STRING",
            "colCnt": 45003,
            "gpNm": "검사",
            "colNm": "자기공명영상촬영(MRI)검진이유_정기검진",
            "tblId": "_KNCC_QS_CKUP",
            "colId": "MRIRE_2",
            "tblNm": "검사",
            "dispFormat": "값이 존재할 경우 정기검진"
        },
        {
            "gpId": "_KNCC_CKUP",
            "colDesc": "자기공명영상촬영(MRI)받은횟수",
            "num": 133,
            "dataType": "INTEGER",
            "colCnt": 17360,
            "gpNm": "검사",
            "colNm": "자기공명영상촬영(MRI)받은횟수",
            "tblId": "_KNCC_QS_CKUP",
            "colId": "MRINUM",
            "tblNm": "검사",
            "dispFormat": "1-9, 모름=9999"
        },
        {
            "gpId": "_KNCC_CKUP",
            "colDesc": "자기공명영상촬영(MRI)검사결과",
            "num": 134,
            "dataType": "STRING",
            "colCnt": 45003,
            "gpNm": "검사",
            "colNm": "자기공명영상촬영(MRI)검사결과",
            "tblId": "_KNCC_QS_CKUP",
            "colId": "MRINR",
            "tblNm": "검사",
            "dispFormat": "1=정상"
        },
        {
            "gpId": "_KNCC_CKUP",
            "colDesc": "자기공명영상촬영(MRI)정상이외",
            "num": 135,
            "dataType": "STRING",
            "colCnt": 45003,
            "gpNm": "검사",
            "colNm": "자기공명영상촬영(MRI)정상이외",
            "tblId": "_KNCC_QS_CKUP",
            "colId": "MRIANR",
            "tblNm": "검사",
            "dispFormat": "텍스트"
        },
        {
            "gpId": "_KNCC_CKUP",
            "colDesc": "자기공명영상촬영(MRI)촬영부위",
            "num": 136,
            "dataType": "STRING",
            "colCnt": 45003,
            "gpNm": "검사",
            "colNm": "자기공명영상촬영(MRI)촬영부위",
            "tblId": "_KNCC_QS_CKUP",
            "colId": "MRIST",
            "tblNm": "검사",
            "dispFormat": "텍스트"
        },
        {
            "gpId": "_KNCC_CKUP",
            "colDesc": "자기공명영상촬영(MRI)처음검사",
            "num": 137,
            "dataType": "STRING",
            "colCnt": 45003,
            "gpNm": "검사",
            "colNm": "자기공명영상촬영(MRI)처음검사",
            "tblId": "_KNCC_QS_CKUP",
            "colId": "MRIFY",
            "tblNm": "검사",
            "dispFormat": "YYYY, 모름=9999"
        },
        {
            "gpId": "_KNCC_CKUP",
            "colDesc": "자기공명영상촬영(MRI)마지막검사",
            "num": 138,
            "dataType": "STRING",
            "colCnt": 45003,
            "gpNm": "검사",
            "colNm": "자기공명영상촬영(MRI)마지막검사",
            "tblId": "_KNCC_QS_CKUP",
            "colId": "MRILY",
            "tblNm": "검사",
            "dispFormat": "YYYY, 모름=9999"
        },
        {
            "gpId": "_KNCC_CKUP",
            "colDesc": "양전자단층촬영(PET)",
            "num": 139,
            "dataType": "STRING",
            "colCnt": 45003,
            "gpNm": "검사",
            "colNm": "양전자단층촬영(PET)",
            "tblId": "_KNCC_QS_CKUP",
            "colId": "PET",
            "tblNm": "검사",
            "dispFormat": "1=있다"
        },
        {
            "gpId": "_KNCC_CKUP",
            "colDesc": "양전자단층촬영(PET)검진이유_이상증상",
            "num": 140,
            "dataType": "STRING",
            "colCnt": 45003,
            "gpNm": "검사",
            "colNm": "양전자단층촬영(PET)검진이유_이상증상",
            "tblId": "_KNCC_QS_CKUP",
            "colId": "PETRE_1",
            "tblNm": "검사",
            "dispFormat": "값이 존재할 경우 이상증상"
        },
        {
            "gpId": "_KNCC_CKUP",
            "colDesc": "양전자단층촬영(PET)검진이유_정기검진",
            "num": 141,
            "dataType": "STRING",
            "colCnt": 45003,
            "gpNm": "검사",
            "colNm": "양전자단층촬영(PET)검진이유_정기검진",
            "tblId": "_KNCC_QS_CKUP",
            "colId": "PETRE_2",
            "tblNm": "검사",
            "dispFormat": "값이 존재할 경우 정기검진"
        },
        {
            "gpId": "_KNCC_CKUP",
            "colDesc": "양전자단층촬영(PET)받은횟수",
            "num": 142,
            "dataType": "INTEGER",
            "colCnt": 691,
            "gpNm": "검사",
            "colNm": "양전자단층촬영(PET)받은횟수",
            "tblId": "_KNCC_QS_CKUP",
            "colId": "PETNUM",
            "tblNm": "검사",
            "dispFormat": "1-9, 모름=9999"
        },
        {
            "gpId": "_KNCC_CKUP",
            "colDesc": "양전자단층촬영(PET)검사결과",
            "num": 143,
            "dataType": "STRING",
            "colCnt": 45003,
            "gpNm": "검사",
            "colNm": "양전자단층촬영(PET)검사결과",
            "tblId": "_KNCC_QS_CKUP",
            "colId": "PETNR",
            "tblNm": "검사",
            "dispFormat": "1=정상"
        },
        {
            "gpId": "_KNCC_CKUP",
            "colDesc": "양전자단층촬영(PET)정상이외",
            "num": 144,
            "dataType": "STRING",
            "colCnt": 45003,
            "gpNm": "검사",
            "colNm": "양전자단층촬영(PET)정상이외",
            "tblId": "_KNCC_QS_CKUP",
            "colId": "PETANR",
            "tblNm": "검사",
            "dispFormat": "텍스트"
        },
        {
            "gpId": "_KNCC_CKUP",
            "colDesc": "양전자단층촬영(PET)촬영부위",
            "num": 145,
            "dataType": "STRING",
            "colCnt": 45003,
            "gpNm": "검사",
            "colNm": "양전자단층촬영(PET)촬영부위",
            "tblId": "_KNCC_QS_CKUP",
            "colId": "PETST",
            "tblNm": "검사",
            "dispFormat": "텍스트"
        },
        {
            "gpId": "_KNCC_CKUP",
            "colDesc": "양전자단층촬영(PET)처음검사",
            "num": 146,
            "dataType": "STRING",
            "colCnt": 45003,
            "gpNm": "검사",
            "colNm": "양전자단층촬영(PET)처음검사",
            "tblId": "_KNCC_QS_CKUP",
            "colId": "PETFY",
            "tblNm": "검사",
            "dispFormat": "YYYY, 모름=9999"
        },
        {
            "gpId": "_KNCC_CKUP",
            "colDesc": "양전자단층촬영(PET)마지막검사",
            "num": 147,
            "dataType": "STRING",
            "colCnt": 45003,
            "gpNm": "검사",
            "colNm": "양전자단층촬영(PET)마지막검사",
            "tblId": "_KNCC_QS_CKUP",
            "colId": "PETLY",
            "tblNm": "검사",
            "dispFormat": "YYYY, 모름=9999"
        },
        {
            "gpId": "_KNCC_CKUP",
            "colDesc": "갑상선혈액검사",
            "num": 148,
            "dataType": "STRING",
            "colCnt": 45003,
            "gpNm": "검사",
            "colNm": "갑상선혈액검사",
            "tblId": "_KNCC_QS_CKUP",
            "colId": "THYR",
            "tblNm": "검사",
            "dispFormat": "1=있다"
        },
        {
            "gpId": "_KNCC_CKUP",
            "colDesc": "갑상선혈액검사검진이유_이상증상",
            "num": 149,
            "dataType": "STRING",
            "colCnt": 45003,
            "gpNm": "검사",
            "colNm": "갑상선혈액검사검진이유_이상증상",
            "tblId": "_KNCC_QS_CKUP",
            "colId": "THYRRE_1",
            "tblNm": "검사",
            "dispFormat": "값이 존재할 경우 이상증상"
        },
        {
            "gpId": "_KNCC_CKUP",
            "colDesc": "갑상선혈액검사검진이유_정기검진",
            "num": 150,
            "dataType": "STRING",
            "colCnt": 45003,
            "gpNm": "검사",
            "colNm": "갑상선혈액검사검진이유_정기검진",
            "tblId": "_KNCC_QS_CKUP",
            "colId": "THYRRE_2",
            "tblNm": "검사",
            "dispFormat": "값이 존재할 경우 정기검진"
        },
        {
            "gpId": "_KNCC_CKUP",
            "colDesc": "갑상선혈액검사받은횟수",
            "num": 151,
            "dataType": "INTEGER",
            "colCnt": 2688,
            "gpNm": "검사",
            "colNm": "갑상선혈액검사받은횟수",
            "tblId": "_KNCC_QS_CKUP",
            "colId": "THYRNUM",
            "tblNm": "검사",
            "dispFormat": "1-9, 모름=9999"
        },
        {
            "gpId": "_KNCC_CKUP",
            "colDesc": "갑상선혈액검사검사결과",
            "num": 152,
            "dataType": "STRING",
            "colCnt": 45003,
            "gpNm": "검사",
            "colNm": "갑상선혈액검사검사결과",
            "tblId": "_KNCC_QS_CKUP",
            "colId": "THYRNR",
            "tblNm": "검사",
            "dispFormat": "1=정상 / 2=결절 / 3=암 / 4=기타"
        },
        {
            "gpId": "_KNCC_CKUP",
            "colDesc": "갑상선혈액검사정상이외",
            "num": 153,
            "dataType": "STRING",
            "colCnt": 45003,
            "gpNm": "검사",
            "colNm": "갑상선혈액검사정상이외",
            "tblId": "_KNCC_QS_CKUP",
            "colId": "THYRNRE",
            "tblNm": "검사",
            "dispFormat": "텍스트"
        },
        {
            "gpId": "_KNCC_CKUP",
            "colDesc": "갑상선혈액검사처음검사",
            "num": 154,
            "dataType": "STRING",
            "colCnt": 45003,
            "gpNm": "검사",
            "colNm": "갑상선혈액검사처음검사",
            "tblId": "_KNCC_QS_CKUP",
            "colId": "THYRFY",
            "tblNm": "검사",
            "dispFormat": "YYYY, 모름=9999"
        },
        {
            "gpId": "_KNCC_CKUP",
            "colDesc": "갑상선혈액검사마지막검사",
            "num": 155,
            "dataType": "STRING",
            "colCnt": 45003,
            "gpNm": "검사",
            "colNm": "갑상선혈액검사마지막검사",
            "tblId": "_KNCC_QS_CKUP",
            "colId": "THYRLY",
            "tblNm": "검사",
            "dispFormat": "YYYY, 모름=9999"
        },
        {
            "gpId": "_KNCC_CKUP",
            "colDesc": "갑상선초음파_설문",
            "num": 156,
            "dataType": "STRING",
            "colCnt": 45003,
            "gpNm": "검사",
            "colNm": "갑상선초음파_설문",
            "tblId": "_KNCC_QS_CKUP",
            "colId": "THSN",
            "tblNm": "검사",
            "dispFormat": "1=있다"
        },
        {
            "gpId": "_KNCC_CKUP",
            "colDesc": "갑상선초음파검진이유_이상증상",
            "num": 157,
            "dataType": "STRING",
            "colCnt": 45003,
            "gpNm": "검사",
            "colNm": "갑상선초음파검진이유_이상증상",
            "tblId": "_KNCC_QS_CKUP",
            "colId": "THSNRE_1",
            "tblNm": "검사",
            "dispFormat": "값이 존재할 경우 이상증상"
        },
        {
            "gpId": "_KNCC_CKUP",
            "colDesc": "갑상선초음파검진이유_정기검진",
            "num": 158,
            "dataType": "STRING",
            "colCnt": 45003,
            "gpNm": "검사",
            "colNm": "갑상선초음파검진이유_정기검진",
            "tblId": "_KNCC_QS_CKUP",
            "colId": "THSNRE_2",
            "tblNm": "검사",
            "dispFormat": "값이 존재할 경우 정기검진"
        },
        {
            "gpId": "_KNCC_CKUP",
            "colDesc": "갑상선초음파받은횟수",
            "num": 159,
            "dataType": "INTEGER",
            "colCnt": 3359,
            "gpNm": "검사",
            "colNm": "갑상선초음파받은횟수",
            "tblId": "_KNCC_QS_CKUP",
            "colId": "THSNNUM",
            "tblNm": "검사",
            "dispFormat": "1-9, 모름=9999"
        },
        {
            "gpId": "_KNCC_CKUP",
            "colDesc": "갑상선초음파검사결과",
            "num": 160,
            "dataType": "STRING",
            "colCnt": 45003,
            "gpNm": "검사",
            "colNm": "갑상선초음파검사결과",
            "tblId": "_KNCC_QS_CKUP",
            "colId": "THSNNR",
            "tblNm": "검사",
            "dispFormat": "텍스트"
        },
        {
            "gpId": "_KNCC_CKUP",
            "colDesc": "갑상선초음파정상이외",
            "num": 161,
            "dataType": "STRING",
            "colCnt": 45003,
            "gpNm": "검사",
            "colNm": "갑상선초음파정상이외",
            "tblId": "_KNCC_QS_CKUP",
            "colId": "THSNNRE",
            "tblNm": "검사",
            "dispFormat": "YYYY, 모름=9999"
        },
        {
            "gpId": "_KNCC_CKUP",
            "colDesc": "갑상선초음파처음검사",
            "num": 162,
            "dataType": "STRING",
            "colCnt": 45003,
            "gpNm": "검사",
            "colNm": "갑상선초음파처음검사",
            "tblId": "_KNCC_QS_CKUP",
            "colId": "THSNFY",
            "tblNm": "검사",
            "dispFormat": "YYYY, 모름=9999"
        },
        {
            "gpId": "_KNCC_CKUP",
            "colDesc": "갑상선초음파마지막검사",
            "num": 163,
            "dataType": "STRING",
            "colCnt": 45003,
            "gpNm": "검사",
            "colNm": "갑상선초음파마지막검사",
            "tblId": "_KNCC_QS_CKUP",
            "colId": "THSNLY",
            "tblNm": "검사",
            "dispFormat": "YYYY, 모름=9999"
        },
        {
            "gpId": "_KNCC_CKUP",
            "colDesc": "산부인과초음파",
            "num": 164,
            "dataType": "STRING",
            "colCnt": 45003,
            "gpNm": "검사",
            "colNm": "산부인과초음파",
            "tblId": "_KNCC_QS_CKUP",
            "colId": "GYSN",
            "tblNm": "검사",
            "dispFormat": "1=있다"
        },
        {
            "gpId": "_KNCC_CKUP",
            "colDesc": "산부인과초음파검진이유_이상증상",
            "num": 165,
            "dataType": "STRING",
            "colCnt": 45003,
            "gpNm": "검사",
            "colNm": "산부인과초음파검진이유_이상증상",
            "tblId": "_KNCC_QS_CKUP",
            "colId": "GYSNRE_1",
            "tblNm": "검사",
            "dispFormat": "값이 존재할 경우 이상증상"
        },
        {
            "gpId": "_KNCC_CKUP",
            "colDesc": "산부인과초음파검진이유_정기검진",
            "num": 166,
            "dataType": "STRING",
            "colCnt": 45003,
            "gpNm": "검사",
            "colNm": "산부인과초음파검진이유_정기검진",
            "tblId": "_KNCC_QS_CKUP",
            "colId": "GYSNRE_2",
            "tblNm": "검사",
            "dispFormat": "값이 존재할 경우 정기검진"
        },
        {
            "gpId": "_KNCC_CKUP",
            "colDesc": "산부인과초음파받은횟수",
            "num": 167,
            "dataType": "INTEGER",
            "colCnt": 4789,
            "gpNm": "검사",
            "colNm": "산부인과초음파받은횟수",
            "tblId": "_KNCC_QS_CKUP",
            "colId": "GYSNNUM",
            "tblNm": "검사",
            "dispFormat": "1-9, 모름=9999"
        },
        {
            "gpId": "_KNCC_CKUP",
            "colDesc": "산부인과초음파검사결과",
            "num": 168,
            "dataType": "STRING",
            "colCnt": 45003,
            "gpNm": "검사",
            "colNm": "산부인과초음파검사결과",
            "tblId": "_KNCC_QS_CKUP",
            "colId": "GYSNNR",
            "tblNm": "검사",
            "dispFormat": "텍스트"
        },
        {
            "gpId": "_KNCC_CKUP",
            "colDesc": "산부인과초음파정상이외",
            "num": 169,
            "dataType": "STRING",
            "colCnt": 45003,
            "gpNm": "검사",
            "colNm": "산부인과초음파정상이외",
            "tblId": "_KNCC_QS_CKUP",
            "colId": "GYSNANR",
            "tblNm": "검사",
            "dispFormat": "YYYY, 모름=9999"
        },
        {
            "gpId": "_KNCC_CKUP",
            "colDesc": "산부인과초음파처음검사",
            "num": 170,
            "dataType": "STRING",
            "colCnt": 45003,
            "gpNm": "검사",
            "colNm": "산부인과초음파처음검사",
            "tblId": "_KNCC_QS_CKUP",
            "colId": "GYSNFY",
            "tblNm": "검사",
            "dispFormat": "YYYY, 모름=9999"
        },
        {
            "gpId": "_KNCC_CKUP",
            "colDesc": "산부인과초음파마지막검사",
            "num": 171,
            "dataType": "STRING",
            "colCnt": 45003,
            "gpNm": "검사",
            "colNm": "산부인과초음파마지막검사",
            "tblId": "_KNCC_QS_CKUP",
            "colId": "GYSNLY",
            "tblNm": "검사",
            "dispFormat": "YYYY, 모름=9999"
        },
        {
            "gpId": "_KNCC_CKUP",
            "colDesc": "산부인과골반진찰",
            "num": 172,
            "dataType": "STRING",
            "colCnt": 45003,
            "gpNm": "검사",
            "colNm": "산부인과골반진찰",
            "tblId": "_KNCC_QS_CKUP",
            "colId": "PVEX",
            "tblNm": "검사",
            "dispFormat": "1=있다"
        },
        {
            "gpId": "_KNCC_CKUP",
            "colDesc": "산부인과골반진찰검진이유_이상증상",
            "num": 173,
            "dataType": "STRING",
            "colCnt": 45003,
            "gpNm": "검사",
            "colNm": "산부인과골반진찰검진이유_이상증상",
            "tblId": "_KNCC_QS_CKUP",
            "colId": "PVEXRE_1",
            "tblNm": "검사",
            "dispFormat": "값이 존재할 경우 이상증상"
        },
        {
            "gpId": "_KNCC_CKUP",
            "colDesc": "산부인과골반진찰검진이유_정기검진",
            "num": 174,
            "dataType": "STRING",
            "colCnt": 45003,
            "gpNm": "검사",
            "colNm": "산부인과골반진찰검진이유_정기검진",
            "tblId": "_KNCC_QS_CKUP",
            "colId": "PVEXRE_2",
            "tblNm": "검사",
            "dispFormat": "값이 존재할 경우 정기검진"
        },
        {
            "gpId": "_KNCC_CKUP",
            "colDesc": "산부인과골반진찰받은횟수",
            "num": 175,
            "dataType": "STRING",
            "colCnt": 45003,
            "gpNm": "검사",
            "colNm": "산부인과골반진찰받은횟수",
            "tblId": "_KNCC_QS_CKUP",
            "colId": "PVEXNUM",
            "tblNm": "검사",
            "dispFormat": "1-9, 모름=9999"
        },
        {
            "gpId": "_KNCC_CKUP",
            "colDesc": "산부인과골반진찰검사결과",
            "num": 176,
            "dataType": "STRING",
            "colCnt": 45003,
            "gpNm": "검사",
            "colNm": "산부인과골반진찰검사결과",
            "tblId": "_KNCC_QS_CKUP",
            "colId": "PVEXNR",
            "tblNm": "검사",
            "dispFormat": "텍스트"
        },
        {
            "gpId": "_KNCC_CKUP",
            "colDesc": "산부인과골반진찰정상이외",
            "num": 177,
            "dataType": "STRING",
            "colCnt": 45003,
            "gpNm": "검사",
            "colNm": "산부인과골반진찰정상이외",
            "tblId": "_KNCC_QS_CKUP",
            "colId": "PVEXANR",
            "tblNm": "검사",
            "dispFormat": "YYYY, 모름=9999"
        },
        {
            "gpId": "_KNCC_CKUP",
            "colDesc": "산부인과골반진찰처음검사",
            "num": 178,
            "dataType": "STRING",
            "colCnt": 45003,
            "gpNm": "검사",
            "colNm": "산부인과골반진찰처음검사",
            "tblId": "_KNCC_QS_CKUP",
            "colId": "PVEXFY",
            "tblNm": "검사",
            "dispFormat": "YYYY, 모름=9999"
        },
        {
            "gpId": "_KNCC_CKUP",
            "colDesc": "산부인과골반진찰마지막검사",
            "num": 179,
            "dataType": "STRING",
            "colCnt": 45003,
            "gpNm": "검사",
            "colNm": "산부인과골반진찰마지막검사",
            "tblId": "_KNCC_QS_CKUP",
            "colId": "PVEXLY",
            "tblNm": "검사",
            "dispFormat": "YYYY, 모름=9999"
        },
        {
            "gpId": "_KNCC_CKUP",
            "colDesc": "인유두종바이러스(HPV)",
            "num": 180,
            "dataType": "STRING",
            "colCnt": 45003,
            "gpNm": "검사",
            "colNm": "인유두종바이러스(HPV)",
            "tblId": "_KNCC_QS_CKUP",
            "colId": "HPV",
            "tblNm": "검사",
            "dispFormat": "1=있다"
        },
        {
            "gpId": "_KNCC_CKUP",
            "colDesc": "인유두종바이러스(HPV)검진이유_이상증상",
            "num": 181,
            "dataType": "STRING",
            "colCnt": 45003,
            "gpNm": "검사",
            "colNm": "인유두종바이러스(HPV)검진이유_이상증상",
            "tblId": "_KNCC_QS_CKUP",
            "colId": "HPVRE_1",
            "tblNm": "검사",
            "dispFormat": "값이 존재할 경우 이상증상"
        },
        {
            "gpId": "_KNCC_CKUP",
            "colDesc": "인유두종바이러스(HPV)검진이유_정기검진",
            "num": 182,
            "dataType": "STRING",
            "colCnt": 45003,
            "gpNm": "검사",
            "colNm": "인유두종바이러스(HPV)검진이유_정기검진",
            "tblId": "_KNCC_QS_CKUP",
            "colId": "HPVRE_2",
            "tblNm": "검사",
            "dispFormat": "값이 존재할 경우 정기검진"
        },
        {
            "gpId": "_KNCC_CKUP",
            "colDesc": "인유두종바이러스(HPV)받은횟수",
            "num": 183,
            "dataType": "INTEGER",
            "colCnt": 462,
            "gpNm": "검사",
            "colNm": "인유두종바이러스(HPV)받은횟수",
            "tblId": "_KNCC_QS_CKUP",
            "colId": "HPVNUM",
            "tblNm": "검사",
            "dispFormat": "1-9까지 입력, 모름=9999"
        },
        {
            "gpId": "_KNCC_CKUP",
            "colDesc": "인유두종바이러스(HPV)검사결과",
            "num": 184,
            "dataType": "STRING",
            "colCnt": 45003,
            "gpNm": "검사",
            "colNm": "인유두종바이러스(HPV)검사결과",
            "tblId": "_KNCC_QS_CKUP",
            "colId": "HPVNR",
            "tblNm": "검사",
            "dispFormat": "1=정상 / 2=비정상(양성) / 3=결과모름 / 4=이전 양성에서 음성"
        },
        {
            "gpId": "_KNCC_CKUP",
            "colDesc": "인유두종바이러스(HPV)처음검사",
            "num": 185,
            "dataType": "STRING",
            "colCnt": 45003,
            "gpNm": "검사",
            "colNm": "인유두종바이러스(HPV)처음검사",
            "tblId": "_KNCC_QS_CKUP",
            "colId": "HPVFY",
            "tblNm": "검사",
            "dispFormat": "YYYY, 모름=9999"
        },
        {
            "gpId": "_KNCC_CKUP",
            "colDesc": "인유두종바이러스(HPV)마지막검사",
            "num": 186,
            "dataType": "STRING",
            "colCnt": 45003,
            "gpNm": "검사",
            "colNm": "인유두종바이러스(HPV)마지막검사",
            "tblId": "_KNCC_QS_CKUP",
            "colId": "HPVLY",
            "tblNm": "검사",
            "dispFormat": "YYYY, 모름=9999"
        },
        {
            "gpId": "_KNCC_CKUP",
            "colDesc": "자궁암검사",
            "num": 187,
            "dataType": "STRING",
            "colCnt": 45003,
            "gpNm": "검사",
            "colNm": "자궁암검사",
            "tblId": "_KNCC_QS_CKUP",
            "colId": "UT",
            "tblNm": "검사",
            "dispFormat": "1=있다"
        },
        {
            "gpId": "_KNCC_CKUP",
            "colDesc": "자궁암검사검진이유_이상증상",
            "num": 188,
            "dataType": "STRING",
            "colCnt": 45003,
            "gpNm": "검사",
            "colNm": "자궁암검사검진이유_이상증상",
            "tblId": "_KNCC_QS_CKUP",
            "colId": "UTRE_1",
            "tblNm": "검사",
            "dispFormat": "값이 존재할 경우 이상증상"
        },
        {
            "gpId": "_KNCC_CKUP",
            "colDesc": "자궁암검사검진이유_정기검진",
            "num": 189,
            "dataType": "STRING",
            "colCnt": 45003,
            "gpNm": "검사",
            "colNm": "자궁암검사검진이유_정기검진",
            "tblId": "_KNCC_QS_CKUP",
            "colId": "UTRE_2",
            "tblNm": "검사",
            "dispFormat": "값이 존재할 경우 정기검진"
        },
        {
            "gpId": "_KNCC_CKUP",
            "colDesc": "자궁암검사받은횟수",
            "num": 190,
            "dataType": "STRING",
            "colCnt": 45003,
            "gpNm": "검사",
            "colNm": "자궁암검사받은횟수",
            "tblId": "_KNCC_QS_CKUP",
            "colId": "UTNUM",
            "tblNm": "검사",
            "dispFormat": "1-9까지 입력, 모름=9999"
        },
        {
            "gpId": "_KNCC_CKUP",
            "colDesc": "자궁암검사검사결과",
            "num": 191,
            "dataType": "STRING",
            "colCnt": 45003,
            "gpNm": "검사",
            "colNm": "자궁암검사검사결과",
            "tblId": "_KNCC_QS_CKUP",
            "colId": "UTNR",
            "tblNm": "검사",
            "dispFormat": "1=정상"
        },
        {
            "gpId": "_KNCC_CKUP",
            "colDesc": "자궁암검사정상이외",
            "num": 192,
            "dataType": "STRING",
            "colCnt": 45003,
            "gpNm": "검사",
            "colNm": "자궁암검사정상이외",
            "tblId": "_KNCC_QS_CKUP",
            "colId": "UTANR",
            "tblNm": "검사",
            "dispFormat": "텍스트"
        },
        {
            "gpId": "_KNCC_CKUP",
            "colDesc": "자궁암검사처음검사",
            "num": 193,
            "dataType": "STRING",
            "colCnt": 45003,
            "gpNm": "검사",
            "colNm": "자궁암검사처음검사",
            "tblId": "_KNCC_QS_CKUP",
            "colId": "UTFY",
            "tblNm": "검사",
            "dispFormat": "YYYY, 모름=9999"
        },
        {
            "gpId": "_KNCC_CKUP",
            "colDesc": "자궁암검사마지막검사",
            "num": 194,
            "dataType": "STRING",
            "colCnt": 45003,
            "gpNm": "검사",
            "colNm": "자궁암검사마지막검사",
            "tblId": "_KNCC_QS_CKUP",
            "colId": "UTLY",
            "tblNm": "검사",
            "dispFormat": "YYYY, 모름=9999"
        },
        {
            "gpId": "_KNCC_CKUP",
            "colDesc": "간염검사(2007년 이전)",
            "num": 195,
            "dataType": "STRING",
            "colCnt": 45003,
            "gpNm": "검사",
            "colNm": "간염검사",
            "tblId": "_KNCC_QS_CKUP",
            "colId": "HTEST5",
            "tblNm": "검사",
            "dispFormat": "1:있다/0:없다/99:모름"
        },
        {
            "gpId": "_KNCC_CKUP",
            "colDesc": "간염검사받은년도(2007년 이전)",
            "num": 196,
            "dataType": "STRING",
            "colCnt": 45003,
            "gpNm": "검사",
            "colNm": "간염검사받은년도",
            "tblId": "_KNCC_QS_CKUP",
            "colId": "HTEST5_Y",
            "tblNm": "검사",
            "dispFormat": "년도입력/0:없다/9999:모름"
        },
        {
            "gpId": "_KNCC_CKUP",
            "colDesc": "간염검사받은횟수(2007년 이전)",
            "num": 197,
            "dataType": "STRING",
            "colCnt": 45003,
            "gpNm": "검사",
            "colNm": "간염검사받은횟수",
            "tblId": "_KNCC_QS_CKUP",
            "colId": "HTEST5_T",
            "tblNm": "검사",
            "dispFormat": "횟수입력/0:없다/99:모름"
        },
        {
            "gpId": "_KNCC_CKUP",
            "colDesc": "간초음파(2007년 이전)",
            "num": 198,
            "dataType": "STRING",
            "colCnt": 45003,
            "gpNm": "검사",
            "colNm": "간초음파",
            "tblId": "_KNCC_QS_CKUP",
            "colId": "HTEST6",
            "tblNm": "검사",
            "dispFormat": "1:있다/0:없다/99:모름"
        },
        {
            "gpId": "_KNCC_CKUP",
            "colDesc": "간초음파받은년도(2007년 이전)",
            "num": 199,
            "dataType": "STRING",
            "colCnt": 45003,
            "gpNm": "검사",
            "colNm": "간초음파받은년도",
            "tblId": "_KNCC_QS_CKUP",
            "colId": "HTEST6_Y",
            "tblNm": "검사",
            "dispFormat": "년도입력/0:없다/9999:모름"
        },
        {
            "gpId": "_KNCC_CKUP",
            "colDesc": "간초음파받은횟수(2007년 이전)",
            "num": 200,
            "dataType": "STRING",
            "colCnt": 45003,
            "gpNm": "검사",
            "colNm": "간초음파받은횟수",
            "tblId": "_KNCC_QS_CKUP",
            "colId": "HTEST6_T",
            "tblNm": "검사",
            "dispFormat": "횟수입력/0:없다/99:모름"
        },
        {
            "gpId": "_KNCC_CKUP",
            "colDesc": "컴퓨터촬영(2007년 이전)",
            "num": 201,
            "dataType": "STRING",
            "colCnt": 45003,
            "gpNm": "검사",
            "colNm": "컴퓨터촬영",
            "tblId": "_KNCC_QS_CKUP",
            "colId": "HTEST19",
            "tblNm": "검사",
            "dispFormat": "1:있다/0:없다/99:모름"
        },
        {
            "gpId": "_KNCC_CKUP",
            "colDesc": "컴퓨터촬영받은년도(2007년 이전)",
            "num": 202,
            "dataType": "STRING",
            "colCnt": 45003,
            "gpNm": "검사",
            "colNm": "컴퓨터촬영받은년도",
            "tblId": "_KNCC_QS_CKUP",
            "colId": "HTEST19_Y",
            "tblNm": "검사",
            "dispFormat": "년도입력/0:없다/9999:모름"
        },
        {
            "gpId": "_KNCC_CKUP",
            "colDesc": "컴퓨터촬영받은횟수(2007년 이전)",
            "num": 203,
            "dataType": "STRING",
            "colCnt": 45003,
            "gpNm": "검사",
            "colNm": "컴퓨터촬영받은횟수",
            "tblId": "_KNCC_QS_CKUP",
            "colId": "HTEST19_T",
            "tblNm": "검사",
            "dispFormat": "횟수입력/0:없다/99:모름"
        },
        {
            "gpId": "_KNCC_CKUP",
            "colDesc": "컴퓨터촬영받은부위(2007년 이전)",
            "num": 204,
            "dataType": "STRING",
            "colCnt": 45003,
            "gpNm": "검사",
            "colNm": "컴퓨터촬영받은부위",
            "tblId": "_KNCC_QS_CKUP",
            "colId": "HTEST19_S",
            "tblNm": "검사",
            "dispFormat": "부위 정보"
        },
        {
            "gpId": "_KNCC_CKUP",
            "colDesc": "방사선치료(2007년 이전)",
            "num": 205,
            "dataType": "STRING",
            "colCnt": 45003,
            "gpNm": "검사",
            "colNm": "방사선치료",
            "tblId": "_KNCC_QS_CKUP",
            "colId": "HTEST20",
            "tblNm": "검사",
            "dispFormat": "1:있다/0:없다/99:모름"
        },
        {
            "gpId": "_KNCC_CKUP",
            "colDesc": "방사선치료받은년도(2007년 이전)",
            "num": 206,
            "dataType": "STRING",
            "colCnt": 45003,
            "gpNm": "검사",
            "colNm": "방사선치료받은년도",
            "tblId": "_KNCC_QS_CKUP",
            "colId": "HTEST20_Y",
            "tblNm": "검사",
            "dispFormat": "년도입력/0:없다/9999:모름"
        },
        {
            "gpId": "_KNCC_CKUP",
            "colDesc": "방사선치료받은횟수(2007년 이전)",
            "num": 207,
            "dataType": "STRING",
            "colCnt": 45003,
            "gpNm": "검사",
            "colNm": "방사선치료받은횟수",
            "tblId": "_KNCC_QS_CKUP",
            "colId": "HTEST20_T",
            "tblNm": "검사",
            "dispFormat": "횟수입력/0:없다/99:모름"
        },
        {
            "gpId": "_KNCC_CKUP",
            "colDesc": "방사선치료받은부위(2007년 이전)",
            "num": 208,
            "dataType": "STRING",
            "colCnt": 45003,
            "gpNm": "검사",
            "colNm": "방사선치료받은부위",
            "tblId": "_KNCC_QS_CKUP",
            "colId": "HTEST20_S",
            "tblNm": "검사",
            "dispFormat": "부위 정보"
        },
        {
            "gpId": "_KNCC_CKUP",
            "colDesc": "X선사진촬영(2007년 이전)",
            "num": 209,
            "dataType": "STRING",
            "colCnt": 45003,
            "gpNm": "검사",
            "colNm": "X선사진촬영",
            "tblId": "_KNCC_QS_CKUP",
            "colId": "HTEST21",
            "tblNm": "검사",
            "dispFormat": "1:있다/0:없다/99:모름"
        },
        {
            "gpId": "_KNCC_CKUP",
            "colDesc": "X선사진촬영받은년도(2007년 이전)",
            "num": 210,
            "dataType": "STRING",
            "colCnt": 45003,
            "gpNm": "검사",
            "colNm": "X선사진촬영받은년도",
            "tblId": "_KNCC_QS_CKUP",
            "colId": "HTEST21_Y",
            "tblNm": "검사",
            "dispFormat": "년도입력/0:없다/9999:모름"
        },
        {
            "gpId": "_KNCC_CKUP",
            "colDesc": "X선사진촬영받은횟수(2007년 이전)",
            "num": 211,
            "dataType": "STRING",
            "colCnt": 45003,
            "gpNm": "검사",
            "colNm": "X선사진촬영받은횟수",
            "tblId": "_KNCC_QS_CKUP",
            "colId": "HTEST21_T",
            "tblNm": "검사",
            "dispFormat": "횟수입력/0:없다/99:모름"
        },
        {
            "gpId": "_KNCC_CKUP",
            "colDesc": "X선사진촬영받은부위(2007년 이전)",
            "num": 212,
            "dataType": "STRING",
            "colCnt": 45003,
            "gpNm": "검사",
            "colNm": "X선사진촬영받은부위",
            "tblId": "_KNCC_QS_CKUP",
            "colId": "HTEST21_S",
            "tblNm": "검사",
            "dispFormat": "부위 정보"
        },
        {
            "gpId": "_KNCC_CKUP",
            "colDesc": "자궁초음파(2007년 이전)",
            "num": 213,
            "dataType": "STRING",
            "colCnt": 45003,
            "gpNm": "검사",
            "colNm": "자궁초음파",
            "tblId": "_KNCC_QS_CKUP",
            "colId": "HTEST23",
            "tblNm": "검사",
            "dispFormat": "1:있다/0:없다/99:모름"
        },
        {
            "gpId": "_KNCC_CKUP",
            "colDesc": "자궁초음파받은년도(2007년 이전)",
            "num": 214,
            "dataType": "STRING",
            "colCnt": 45003,
            "gpNm": "검사",
            "colNm": "자궁초음파받은년도",
            "tblId": "_KNCC_QS_CKUP",
            "colId": "HTEST23_Y",
            "tblNm": "검사",
            "dispFormat": "년도입력/0:없다/9999:모름"
        },
        {
            "gpId": "_KNCC_CKUP",
            "colDesc": "자궁초음파받은횟수(2007년 이전)",
            "num": 215,
            "dataType": "STRING",
            "colCnt": 45003,
            "gpNm": "검사",
            "colNm": "자궁초음파받은횟수",
            "tblId": "_KNCC_QS_CKUP",
            "colId": "HTEST23_T",
            "tblNm": "검사",
            "dispFormat": "횟수입력/0:없다/99:모름"
        },
        {
            "gpId": "_KNCC_CKUP",
            "colDesc": "기타검사(2007년 이전)",
            "num": 216,
            "dataType": "STRING",
            "colCnt": 45003,
            "gpNm": "검사",
            "colNm": "기타검사",
            "tblId": "_KNCC_QS_CKUP",
            "colId": "HTEST17",
            "tblNm": "검사",
            "dispFormat": "1:있다/0:없다/99:모름"
        },
        {
            "gpId": "_KNCC_CKUP",
            "colDesc": "기타검사받은년도(2007년 이전)",
            "num": 217,
            "dataType": "STRING",
            "colCnt": 45003,
            "gpNm": "검사",
            "colNm": "기타검사받은년도",
            "tblId": "_KNCC_QS_CKUP",
            "colId": "HTEST17_Y",
            "tblNm": "검사",
            "dispFormat": "년도입력/0:없다/9999:모름"
        },
        {
            "gpId": "_KNCC_CKUP",
            "colDesc": "기타검사받은횟수(2007년 이전)",
            "num": 218,
            "dataType": "STRING",
            "colCnt": 45003,
            "gpNm": "검사",
            "colNm": "기타검사받은횟수",
            "tblId": "_KNCC_QS_CKUP",
            "colId": "HTEST17_T",
            "tblNm": "검사",
            "dispFormat": "횟수입력/0:없다/99:모름"
        },
        {
            "gpId": "_KNCC_CKUP",
            "colDesc": "간CT(2007년 이전)",
            "num": 219,
            "dataType": "STRING",
            "colCnt": 45003,
            "gpNm": "검사",
            "colNm": "간CT",
            "tblId": "_KNCC_QS_CKUP",
            "colId": "HTEST7",
            "tblNm": "검사",
            "dispFormat": "1:있다/0:없다/99:모름"
        },
        {
            "gpId": "_KNCC_CKUP",
            "colDesc": "흉부X선촬영(2007년 이전)",
            "num": 220,
            "dataType": "STRING",
            "colCnt": 45003,
            "gpNm": "검사",
            "colNm": "흉부X선촬영",
            "tblId": "_KNCC_QS_CKUP",
            "colId": "HTEST8",
            "tblNm": "검사",
            "dispFormat": "1:있다/0:없다/99:모름"
        },
        {
            "gpId": "_KNCC_CKUP",
            "colDesc": "흉부CT(2007년 이전)",
            "num": 221,
            "dataType": "STRING",
            "colCnt": 45003,
            "gpNm": "검사",
            "colNm": "흉부CT",
            "tblId": "_KNCC_QS_CKUP",
            "colId": "HTEST9",
            "tblNm": "검사",
            "dispFormat": "1:있다/0:없다/99:모름"
        },
        {
            "gpId": "_KNCC_CKUP",
            "colDesc": "방사선치료2(2007년 이전)",
            "num": 222,
            "dataType": "STRING",
            "colCnt": 45003,
            "gpNm": "검사",
            "colNm": "방사선치료2",
            "tblId": "_KNCC_QS_CKUP",
            "colId": "HTEST13",
            "tblNm": "검사",
            "dispFormat": "1:있다/0:없다/99:모름"
        },
        {
            "gpId": "_KNCC_CKUP",
            "colDesc": "동위원소 촬영(2007년 이전)",
            "num": 223,
            "dataType": "STRING",
            "colCnt": 45003,
            "gpNm": "검사",
            "colNm": "동위원소 촬영",
            "tblId": "_KNCC_QS_CKUP",
            "colId": "HTEST16",
            "tblNm": "검사",
            "dispFormat": "1:있다/0:없다/99:모름"
        }
    ],
    "totalCount": 223,
    "pageNo": 1,
    "numOfRows": 300
}